{
  "id": "task098",
  "hash": "4347f46a",
  "description": "Likely rearranges, completes, or recolors existing objects while preserving the canvas and color set. Colors are preserved as a set, though positions may change. Primary structural cue: same colors. Inferred transformation family: move/complete/recolor. The rule is likely but may need pixel-level refinement.",
  "arcDslCode": "from dsl import *\nfrom constants import *\n\n\ndef solve_4347f46a(I):\n    x1 = objects(I, T, F, T)\n    x2 = fork(difference, toindices, box)\n    x3 = mapply(x2, x1)\n    O = fill(I, ZERO, x3)\n    return O\n",
  "shape": "same size"
}
